bandwidth_monitor/__init__.py
bandwidth_monitor/__main__.py
bandwidth_monitor-0.3.0.dist-info/LICENSE.txt
bandwidth_monitor-0.3.0.dist-info/METADATA
bandwidth_monitor-0.3.0.dist-info/WHEEL
bandwidth_monitor-0.3.0.dist-info/top_level.txt
bandwidth_monitor-0.3.0.dist-info/zip-safe
bandwidth_monitor-0.3.0.dist-info/RECORD
