Metadata-Version: 2.1
Name: bandwidth-monitor
Version: 0.3.0
Summary: A wrapper for speedtest.net to get time-series data on local bandwidth availability.
Home-page: https://github.com/mburszley/bandwidth-monitor
Author: Maximilian Burszley
Author-email: mburszley@gmail.com
License: MIT
Platform: UNKNOWN
Classifier: Development Status :: 2 - Pre-Alpha
Classifier: Environment :: Console
Classifier: Intended Audience :: Developers
Classifier: License :: OSI Approved :: MIT License
Classifier: Natural Language :: English
Classifier: Operating System :: OS Independent
Classifier: Programming Language :: Python :: 3 :: Only
Classifier: Topic :: System :: Networking :: Monitoring
Classifier: Typing :: Typed
Requires-Python: >=3.6.0
Requires-Dist: schedule (~=0.6.0)
Requires-Dist: speedtest-cli (~=2.1.0)
